[
  {
    "status": "ok",
    "책 번호": "1번의 책 상세페이지 정보",
    "list": [
      {
        "seq": 1,
        "title": "불편한 편의점",
        "author": "김호연",
        "regDt": "2021-04-19T15:00:00.000+00:00",
        "publisher": "나무옆의자",
        "price": 12600,
        "image": "이미지.img",
        "category": "한국소설일반",
        "bdiSeq": 2,
        "subtitle": "숲속의 현자가 전하는 마지막 인생수업",
        "discount": 0.1,
        "translater": "박미경",
        "overview": "2022년 모두가 잊지 못할 삶과 지혜,\r\n『내가 틀릴 수도 있습니다』한정판 화이트 에디션 출간\r\n“당신은 어떤 사람이며, 어떤 삶을 살고 있습니까?”\r\n2022년 1월, 한 사람이 세상을 떠났다. ‘망설임도, 두려움도 없이 떠납니다’라는 한마디를 남기고. 거대한 애도의 물결이 스웨덴을 휩쓸었다. 비욘 나티코 린데블라드. 수많은 스웨덴인들을 불안에서 끌어내어 평화와 고요로 이끌었던 그는 2018년 루게릭병에 진단받은 후에도 유쾌하고 따뜻한 지혜를 전했다. 20대에 눈부신 사회적 성공을 거뒀지만 모든 것을 버리고 숲속으로 17년간 수행을 떠났던 저자의 여정과 깨달음, 그리고 마지막을 담은 책 『내가 틀릴 수도 있습니다』는 스웨덴에 이어 한국에서도 세대를 불문하고 독자들에게 사랑받으며 출간 이래 베스트셀러의 자리를 지켰다.\r\n올 겨울, 『내가 틀릴 수도 있습니다』의 감동과 깨달음을 더욱 직관적으로 전달하는 토마스 산체스의 새로운 그림을 표지로 입고 각양장 화이트 에디션이 출간되었다. 화이트 에디션에는 나티코의 지혜를 온전히 내 것으로 만들 수 있도록 필사 노트가 함께 제공된다. 한 해를 맺고 시작하는 이 시간을 두려움과 불안 대신 설렘과 용기로 마주하게 해줄 지혜가 여기 있다.",
        "soldout": 1,
        "point": 800,
        "bdiBbiSeq": 1
      }
    ]
  }
]